Workbook

Sheet Summary
A1: Finance Dashboard (Monthly Flow + Current Balances)
A3: Selected Month (enter any date): | C3: 46113 | G3: Current Balance Snapshot | J3: How to use
A4: Month Start | B4: =EOMONTH(C3,-1)+1 | C4: Month End | D4: =EOMONTH(C3,0) | G4: Account | H4: Current Balance / Owed | I4: Currency | J4: 1) C3 selects month for monthly tables
G5: Current | H5: ='Current'!B4 | I5: USD | J5: 2) Left tables = selected month flows only
A6: Selected Month - USD Bank Accounts | G6: Chase | H6: ='Chase'!B4 | I6: USD | J6: 3) Right panel = current balances snapshot
A7: Account | B7: Start Balance | C7: Money In | D7: Money Out | E7: Tax | F7: Net Flow | G7: Wellsfargo | H7: ='Wellsfargo'!B4 | I7: USD | J7: 4) Timeline is collapsed (use + to expand)
A8: Current | B8: =IFERROR(LOOKUP(2,1/(('Current'!A:A<$B$4)*('Current'!G:G<>"")),'Current'!G:G),'Current'!B3) | C8: =SUMIFS('Current'!D:D,'Current'!A:A,">="&$B$4,'Current'!A:A,"<="&$D$4) | D8: =SUMIFS('Current'!E:E,'Current'!A:A,">="&$B$4,'Current'!A:A,"<="&$D$4) | E8: =SUMIFS('Current'!F:F,'Current'!A:A,">="&$B$4,'Current'!A:A,"<="&$D$4) | F8: =C8-D8-E8 | G8: Vyral | H8: ='Vyral'!B4 | I8: USD
A9: Chase | B9: =IFERROR(LOOKUP(2,1/(('Chase'!A:A<$B$4)*('Chase'!G:G<>"")),'Chase'!G:G),'Chase'!B3) | C9: =SUMIFS('Chase'!D:D,'Chase'!A:A,">="&$B$4,'Chase'!A:A,"<="&$D$4) | D9: =SUMIFS('Chase'!E:E,'Chase'!A:A,">="&$B$4,'Chase'!A:A,"<="&$D$4) | E9: =SUMIFS('Chase'!F:F,'Chase'!A:A,">="&$B$4,'Chase'!A:A,"<="&$D$4) | F9: =C9-D9-E9 | G9: Chime | H9: ='Chime'!B4 | I9: USD
A10: Wellsfargo | B10: =IFERROR(LOOKUP(2,1/(('Wellsfargo'!A:A<$B$4)*('Wellsfargo'!G:G<>"")),'Wellsfargo'!G:G),'Wellsfargo'!B3) | C10: =SUMIFS('Wellsfargo'!D:D,'Wellsfargo'!A:A,">="&$B$4,'Wellsfargo'!A:A,"<="&$D$4) | D10: =SUMIFS('Wellsfargo'!E:E,'Wellsfargo'!A:A,">="&$B$4,'Wellsfargo'!A:A,"<="&$D$4) | E10: =SUMIFS('Wellsfargo'!F:F,'Wellsfargo'!A:A,">="&$B$4,'Wellsfargo'!A:A,"<="&$D$4) | F10: =C10-D10-E10 | G10: Total USD Bank Balance | H10: =SUM(H5:H9) | I10: USD
A11: Vyral | B11: =IFERROR(LOOKUP(2,1/(('Vyral'!A:A<$B$4)*('Vyral'!G:G<>"")),'Vyral'!G:G),'Vyral'!B3) | C11: =SUMIFS('Vyral'!D:D,'Vyral'!A:A,">="&$B$4,'Vyral'!A:A,"<="&$D$4) | D11: =SUMIFS('Vyral'!E:E,'Vyral'!A:A,">="&$B$4,'Vyral'!A:A,"<="&$D$4) | E11: =SUMIFS('Vyral'!F:F,'Vyral'!A:A,">="&$B$4,'Vyral'!A:A,"<="&$D$4) | F11: =C11-D11-E11 | G11: Ghana City (Bank) | H11: ='Ghana City'!B4 | I11: GHS
A12: Chime | B12: =IFERROR(LOOKUP(2,1/(('Chime'!A:A<$B$4)*('Chime'!G:G<>"")),'Chime'!G:G),'Chime'!B3) | C12: =SUMIFS('Chime'!D:D,'Chime'!A:A,">="&$B$4,'Chime'!A:A,"<="&$D$4) | D12: =SUMIFS('Chime'!E:E,'Chime'!A:A,">="&$B$4,'Chime'!A:A,"<="&$D$4) | E12: =SUMIFS('Chime'!F:F,'Chime'!A:A,">="&$B$4,'Chime'!A:A,"<="&$D$4) | F12: =C12-D12-E12
A13: USD Bank Totals | B13: =SUM(B8:B12) | C13: =SUM(C8:C12) | D13: =SUM(D8:D12) | E13: =SUM(E8:E12) | F13: =SUM(F8:F12) | G13: Credit Card 1 (Owed) | H13: ='Credit Card 1'!B4 | I13: USD
G14: Credit Card 2 (Owed) | H14: ='Credit Card 2'!B4 | I14: USD
G15: Total Credit Cards Owed | H15: =H13+H14 | I15: USD
A16: Selected Month - GHS Bank Accounts | G16: Net USD Position (Banks - Cards) | H16: =H10-H15 | I16: USD
A17: Account | B17: Start Balance | C17: Money In | D17: Money Out | E17: Tax | F17: Net Flow
A18: Ghana City | B18: =IFERROR(LOOKUP(2,1/(('Ghana City'!A:A<$B$4)*('Ghana City'!G:G<>"")),'Ghana City'!G:G),'Ghana City'!B3) | C18: =SUMIFS('Ghana City'!D:D,'Ghana City'!A:A,">="&$B$4,'Ghana City'!A:A,"<="&$D$4) | D18: =SUMIFS('Ghana City'!E:E,'Ghana City'!A:A,">="&$B$4,'Ghana City'!A:A,"<="&$D$4) | E18: =SUMIFS('Ghana City'!F:F,'Ghana City'!A:A,">="&$B$4,'Ghana City'!A:A,"<="&$D$4) | F18: =C18-D18-E18
A21: Selected Month - Credit Cards (USD)
A22: Card | B22: Start Owed | C22: Payments In | D22: Spend Out | E22: Tax | F22: Net Owed Change
A23: Credit Card 1 | B23: =IFERROR(LOOKUP(2,1/(('Credit Card 1'!A:A<$B$4)*('Credit Card 1'!G:G<>"")),'Credit Card 1'!G:G),'Credit Card 1'!B3) | C23: =SUMIFS('Credit Card 1'!D:D,'Credit Card 1'!A:A,">="&$B$4,'Credit Card 1'!A:A,"<="&$D$4) | D23: =SUMIFS('Credit Card 1'!E:E,'Credit Card 1'!A:A,">="&$B$4,'Credit Card 1'!A:A,"<="&$D$4) | E23: =SUMIFS('Credit Card 1'!F:F,'Credit Card 1'!A:A,">="&$B$4,'Credit Card 1'!A:A,"<="&$D$4) | F23: =D23+E23-C23
A24: Credit Card 2 | B24: =IFERROR(LOOKUP(2,1/(('Credit Card 2'!A:A<$B$4)*('Credit Card 2'!G:G<>"")),'Credit Card 2'!G:G),'Credit Card 2'!B3) | C24: =SUMIFS('Credit Card 2'!D:D,'Credit Card 2'!A:A,">="&$B$4,'Credit Card 2'!A:A,"<="&$D$4) | D24: =SUMIFS('Credit Card 2'!E:E,'Credit Card 2'!A:A,">="&$B$4,'Credit Card 2'!A:A,"<="&$D$4) | E24: =SUMIFS('Credit Card 2'!F:F,'Credit Card 2'!A:A,">="&$B$4,'Credit Card 2'!A:A,"<="&$D$4) | F24: =D24+E24-C24
A28: Monthly Timeline (Apr 2026 to Apr 2029) - collapsed by default | J28: Click + on left margin to expand timeline
A29: Month | B29: USD In | C29: USD Out | D29: USD Tax | E29: USD Net | F29: GHS In | G29: GHS Out | H29: GHS Tax | I29: GHS Net | J29: CC Payments | K29: CC Spend | L29: CC Tax | M29: CC Net Owed Change
A30: 46113 | B30: =SUMIFS('Current'!D:D,'Current'!A:A,">="&EOMONTH($A30,-1)+1,'Current'!A:A,"<="&EOMONTH($A30,0)) + SUMIFS('Chase'!D:D,'Chase'!A:A,">="&EOMONTH($A30,-1)+1,'Chase'!A:A,"<="&EOMONTH($A30,0)) + SUMIFS('Wellsfargo'!D:D,'Wellsfargo'!A:A,">="&EOMONTH($A30,-1)+1,'Wellsfargo'!A:A,"<="&EOMONTH($A30,0)) + SUMIFS('Vyral'!D:D,'Vyral'!A:A,">="&EOMONTH($A30,-1)+1,'Vyral'!A:A,"<="&EOMONTH($A30,0)) + SUMIFS('Chime'!D:D,'Chime'!A:A,">="&EOMONTH($A30,-1)+1,'Chime'!A:A,"<="&EOMONTH($A30,0)) | C30: =SUMIFS('Current'!E:E,'Current'!A:A,">="&EOMONTH($A30,-1)+1,'Current'!A:A,"<="&EOMONTH($A30,0)) + SUMIFS('Chase'!E:E,'Chase'!A:A,">="&EOMONTH($A30,-1)+1,'Chase'!A:A,"<="&EOMONTH($A30,0)) + SUMIFS('Wellsfargo'!E:E,'Wellsfargo'!A:A,">="&EOMONTH($A30,-1)+1,'Wellsfargo'!A:A,"<="&EOMONTH($A30,0)) + SUMIFS('Vyral'!E:E,'Vyral'!A:A,">="&EOMONTH($A30,-1)+1,'Vyral'!A:A,"<="&EOMONTH($A30,0)) + SUMIFS('Chime'!E:E,'Chime'!A:A,">="&EOMONTH($A30,-1)+1,'Chime'!A:A,"<="&EOMONTH($A30,0)) | D30: =SUMIFS('Current'!F:F,'Current'!A:A,">="&EOMONTH($A30,-1)+1,'Current'!A:A,"<="&EOMONTH($A30,0)) + SUMIFS('Chase'!F:F,'Chase'!A:A,">="&EOMONTH($A30,-1)+1,'Chase'!A:A,"<="&EOMONTH($A30,0)) + SUMIFS('Wellsfargo'!F:F,'Wellsfargo'!A:A,">="&EOMONTH($A30,-1)+1,'Wellsfargo'!A:A,"<="&EOMONTH($A30,0)) + SUMIFS('Vyral'!F:F,'Vyral'!A:A,">="&EOMONTH($A30,-1)+1,'Vyral'!A:A,"<="&EOMONTH($A30,0)) + SUMIFS('Chime'!F:F,'Chime'!A:A,">="&EOMONTH($A30,-1)+1,'Chime'!A:A,"<="&EOMONTH($A30,0)) | E30: =B30-C30-D30 | F30: =SUMIFS('Ghana City'!D:D,'Ghana City'!A:A,">="&EOMONTH($A30,-1)+1,'Ghana City'!A:A,"<="&EOMONTH($A30,0)) | G30: =SUMIFS('Ghana City'!E:E,'Ghana City'!A:A,">="&EOMONTH($A30,-1)+1,'Ghana City'!A:A,"<="&EOMONTH($A30,0)) | H30: =SUMIFS('Ghana City'!F:F,'Ghana City'!A:A,">="&EOMONTH($A30,-1)+1,'Ghana City'!A:A,"<="&EOMONTH($A30,0)) | I30: =F30-G30-H30 | J30: =SUMIFS('Credit Card 1'!D:D,'Credit Card 1'!A:A,">="&EOMONTH($A30,-1)+1,'Credit Card 1'!A:A,"<="&EOMONTH($A30,0)) + SUMIFS('Credit Card 2'!D:D,'Credit Card 2'!A:A,">="&EOMONTH($A30,-1)+1,'Credit Card 2'!A:A,"<="&EOMONTH($A30,0)) | K30: =SUMIFS('Credit Card 1'!E:E,'Credit Card 1'!A:A,">="&EOMONTH($A30,-1)+1,'Credit Card 1'!A:A,"<="&EOMONTH($A30,0)) + SUMIFS('Credit Card 2'!E:E,'Credit Card 2'!A:A,">="&EOMONTH($A30,-1)+1,'Credit Card 2'!A:A,"<="&EOMONTH($A30,0)) | L30: =SUMIFS('Credit Card 1'!F:F,'Credit Card 1'!A:A,">="&EOMONTH($A30,-1)+1,'Credit Card 1'!A:A,"<="&EOMONTH($A30,0)) + SUMIFS('Credit Card 2'!F:F,'Credit Card 2'!A:A,">="&EOMONTH($A30,-1)+1,'Credit Card 2'!A:A,"<="&EOMONTH($A30,0)) | M30: =K30+L30-J30
A31: 46143 | B31: =SUMIFS('Current'!D:D,'Current'!A:A,">="&EOMONTH($A31,-1)+1,'Current'!A:A,"<="&EOMONTH($A31,0)) + SUMIFS('Chase'!D:D,'Chase'!A:A,">="&EOMONTH($A31,-1)+1,'Chase'!A:A,"<="&EOMONTH($A31,0)) + SUMIFS('Wellsfargo'!D:D,'Wellsfargo'!A:A,">="&EOMONTH($A31,-1)+1,'Wellsfargo'!A:A,"<="&EOMONTH($A31,0)) + SUMIFS('Vyral'!D:D,'Vyral'!A:A,">="&EOMONTH($A31,-1)+1,'Vyral'!A:A,"<="&EOMONTH($A31,0)) + SUMIFS('Chime'!D:D,'Chime'!A:A,">="&EOMONTH($A31,-1)+1,'Chime'!A:A,"<="&EOMONTH($A31,0)) | C31: =SUMIFS('Current'!E:E,'Current'!A:A,">="&EOMONTH($A31,-1)+1,'Current'!A:A,"<="&EOMONTH($A31,0)) + SUMIFS('Chase'!E:E,'Chase'!A:A,">="&EOMONTH($A31,-1)+1,'Chase'!A:A,"<="&EOMONTH($A31,0)) + SUMIFS('Wellsfargo'!E:E,'Wellsfargo'!A:A,">="&EOMONTH($A31,-1)+1,'Wellsfargo'!A:A,"<="&EOMONTH($A31,0)) + SUMIFS('Vyral'!E:E,'Vyral'!A:A,">="&EOMONTH($A31,-1)+1,'Vyral'!A:A,"<="&EOMONTH($A31,0)) + SUMIFS('Chime'!E:E,'Chime'!A:A,">="&EOMONTH($A31,-1)+1,'Chime'!A:A,"<="&EOMONTH($A31,0)) | D31: =SUMIFS('Current'!F:F,'Current'!A:A,">="&EOMONTH($A31,-1)+1,'Current'!A:A,"<="&EOMONTH($A31,0)) + SUMIFS('Chase'!F:F,'Chase'!A:A,">="&EOMONTH($A31,-1)+1,'Chase'!A:A,"<="&EOMONTH($A31,0)) + SUMIFS('Wellsfargo'!F:F,'Wellsfargo'!A:A,">="&EOMONTH($A31,-1)+1,'Wellsfargo'!A:A,"<="&EOMONTH($A31,0)) + SUMIFS('Vyral'!F:F,'Vyral'!A:A,">="&EOMONTH($A31,-1)+1,'Vyral'!A:A,"<="&EOMONTH($A31,0)) + SUMIFS('Chime'!F:F,'Chime'!A:A,">="&EOMONTH($A31,-1)+1,'Chime'!A:A,"<="&EOMONTH($A31,0)) | E31: =B31-C31-D31 | F31: =SUMIFS('Ghana City'!D:D,'Ghana City'!A:A,">="&EOMONTH($A31,-1)+1,'Ghana City'!A:A,"<="&EOMONTH($A31,0)) | G31: =SUMIFS('Ghana City'!E:E,'Ghana City'!A:A,">="&EOMONTH($A31,-1)+1,'Ghana City'!A:A,"<="&EOMONTH($A31,0)) | H31: =SUMIFS('Ghana City'!F:F,'Ghana City'!A:A,">="&EOMONTH($A31,-1)+1,'Ghana City'!A:A,"<="&EOMONTH($A31,0)) | I31: =F31-G31-H31 | J31: =SUMIFS('Credit Card 1'!D:D,'Credit Card 1'!A:A,">="&EOMONTH($A31,-1)+1,'Credit Card 1'!A:A,"<="&EOMONTH($A31,0)) + SUMIFS('Credit Card 2'!D:D,'Credit Card 2'!A:A,">="&EOMONTH($A31,-1)+1,'Credit Card 2'!A:A,"<="&EOMONTH($A31,0)) | K31: =SUMIFS('Credit Card 1'!E:E,'Credit Card 1'!A:A,">="&EOMONTH($A31,-1)+1,'Credit Card 1'!A:A,"<="&EOMONTH($A31,0)) + SUMIFS('Credit Card 2'!E:E,'Credit Card 2'!A:A,">="&EOMONTH($A31,-1)+1,'Credit Card 2'!A:A,"<="&EOMONTH($A31,0)) | L31: =SUMIFS('Credit Card 1'!F:F,'Credit Card 1'!A:A,">="&EOMONTH($A31,-1)+1,'Credit Card 1'!A:A,"<="&EOMONTH($A31,0)) + SUMIFS('Credit Card 2'!F:F,'Credit Card 2'!A:A,">="&EOMONTH($A31,-1)+1,'Credit Card 2'!A:A,"<="&EOMONTH($A31,0)) | M31: =K31+L31-J31
A32: 46174 | B32: =SUMIFS('Current'!D:D,'Current'!A:A,">="&EOMONTH($A32,-1)+1,'Current'!A:A,"<="&EOMONTH($A32,0)) + SUMIFS('Chase'!D:D,'Chase'!A:A,">="&EOMONTH($A32,-1)+1,'Chase'!A:A,"<="&EOMONTH($A32,0)) + SUMIFS('Wellsfargo'!D:D,'Wellsfargo'!A:A,">="&EOMONTH($A32,-1)+1,'Wellsfargo'!A:A,"<="&EOMONTH($A32,0)) + SUMIFS('Vyral'!D:D,'Vyral'!A:A,">="&EOMONTH($A32,-1)+1,'Vyral'!A:A,"<="&EOMONTH($A32,0)) + SUMIFS('Chime'!D:D,'Chime'!A:A,">="&EOMONTH($A32,-1)+1,'Chime'!A:A,"<="&EOMONTH($A32,0)) | C32: =SUMIFS('Current'!E:E,'Current'!A:A,">="&EOMONTH($A32,-1)+1,'Current'!A:A,"<="&EOMONTH($A32,0)) + SUMIFS('Chase'!E:E,'Chase'!A:A,">="&EOMONTH($A32,-1)+1,'Chase'!A:A,"<="&EOMONTH($A32,0)) + SUMIFS('Wellsfargo'!E:E,'Wellsfargo'!A:A,">="&EOMONTH($A32,-1)+1,'Wellsfargo'!A:A,"<="&EOMONTH($A32,0)) + SUMIFS('Vyral'!E:E,'Vyral'!A:A,">="&EOMONTH($A32,-1)+1,'Vyral'!A:A,"<="&EOMONTH($A32,0)) + SUMIFS('Chime'!E:E,'Chime'!A:A,">="&EOMONTH($A32,-1)+1,'Chime'!A:A,"<="&EOMONTH($A32,0)) | D32: =SUMIFS('Current'!F:F,'Current'!A:A,">="&EOMONTH($A32,-1)+1,'Current'!A:A,"<="&EOMONTH($A32,0)) + SUMIFS('Chase'!F:F,'Chase'!A:A,">="&EOMONTH($A32,-1)+1,'Chase'!A:A,"<="&EOMONTH($A32,0)) + SUMIFS('Wellsfargo'!F:F,'Wellsfargo'!A:A,">="&EOMONTH($A32,-1)+1,'Wellsfargo'!A:A,"<="&EOMONTH($A32,0)) + SUMIFS('Vyral'!F:F,'Vyral'!A:A,">="&EOMONTH($A32,-1)+1,'Vyral'!A:A,"<="&EOMONTH($A32,0)) + SUMIFS('Chime'!F:F,'Chime'!A:A,">="&EOMONTH($A32,-1)+1,'Chime'!A:A,"<="&EOMONTH($A32,0)) | E32: =B32-C32-D32 | F32: =SUMIFS('Ghana City'!D:D,'Ghana City'!A:A,">="&EOMONTH($A32,-1)+1,'Ghana City'!A:A,"<="&EOMONTH($A32,0)) | G32: =SUMIFS('Ghana City'!E:E,'Ghana City'!A:A,">="&EOMONTH($A32,-1)+1,'Ghana City'!A:A,"<="&EOMONTH($A32,0)) | H32: =SUMIFS('Ghana City'!F:F,'Ghana City'!A:A,">="&EOMONTH($A32,-1)+1,'Ghana City'!A:A,"<="&EOMONTH($A32,0)) | I32: =F32-G32-H32 | J32: =SUMIFS('Credit Card 1'!D:D,'Credit Card 1'!A:A,">="&EOMONTH($A32,-1)+1,'Credit Card 1'!A:A,"<="&EOMONTH($A32,0)) + SUMIFS('Credit Card 2'!D:D,'Credit Card 2'!A:A,">="&EOMONTH($A32,-1)+1,'Credit Card 2'!A:A,"<="&EOMONTH($A32,0)) | K32: =SUMIFS('Credit Card 1'!E:E,'Credit Card 1'!A:A,">="&EOMONTH($A32,-1)+1,'Credit Card 1'!A:A,"<="&EOMONTH($A32,0)) + SUMIFS('Credit Card 2'!E:E,'Credit Card 2'!A:A,">="&EOMONTH($A32,-1)+1,'Credit Card 2'!A:A,"<="&EOMONTH($A32,0)) | L32: =SUMIFS('Credit Card 1'!F:F,'Credit Card 1'!A:A,">="&EOMONTH($A32,-1)+1,'Credit Card 1'!A:A,"<="&EOMONTH($A32,0)) + SUMIFS('Credit Card 2'!F:F,'Credit Card 2'!A:A,">="&EOMONTH($A32,-1)+1,'Credit Card 2'!A:A,"<="&EOMONTH($A32,0)) | M32: =K32+L32-J32
A33: 46204 | B33: =SUMIFS('Current'!D:D,'Current'!A:A,">="&EOMONTH($A33,-1)+1,'Current'!A:A,"<="&EOMONTH($A33,0)) + SUMIFS('Chase'!D:D,'Chase'!A:A,">="&EOMONTH($A33,-1)+1,'Chase'!A:A,"<="&EOMONTH($A33,0)) + SUMIFS('Wellsfargo'!D:D,'Wellsfargo'!A:A,">="&EOMONTH($A33,-1)+1,'Wellsfargo'!A:A,"<="&EOMONTH($A33,0)) + SUMIFS('Vyral'!D:D,'Vyral'!A:A,">="&EOMONTH($A33,-1)+1,'Vyral'!A:A,"<="&EOMONTH($A33,0)) + SUMIFS('Chime'!D:D,'Chime'!A:A,">="&EOMONTH($A33,-1)+1,'Chime'!A:A,"<="&EOMONTH($A33,0)) | C33: =SUMIFS('Current'!E:E,'Current'!A:A,">="&EOMONTH($A33,-1)+1,'Current'!A:A,"<="&EOMONTH($A33,0)) + SUMIFS('Chase'!E:E,'Chase'!A:A,">="&EOMONTH($A33,-1)+1,'Chase'!A:A,"<="&EOMONTH($A33,0)) + SUMIFS('Wellsfargo'!E:E,'Wellsfargo'!A:A,">="&EOMONTH($A33,-1)+1,'Wellsfargo'!A:A,"<="&EOMONTH($A33,0)) + SUMIFS('Vyral'!E:E,'Vyral'!A:A,">="&EOMONTH($A33,-1)+1,'Vyral'!A:A,"<="&EOMONTH($A33,0)) + SUMIFS('Chime'!E:E,'Chime'!A:A,">="&EOMONTH($A33,-1)+1,'Chime'!A:A,"<="&EOMONTH($A33,0)) | D33: =SUMIFS('Current'!F:F,'Current'!A:A,">="&EOMONTH($A33,-1)+1,'Current'!A:A,"<="&EOMONTH($A33,0)) + SUMIFS('Chase'!F:F,'Chase'!A:A,">="&EOMONTH($A33,-1)+1,'Chase'!A:A,"<="&EOMONTH($A33,0)) + SUMIFS('Wellsfargo'!F:F,'Wellsfargo'!A:A,">="&EOMONTH($A33,-1)+1,'Wellsfargo'!A:A,"<="&EOMONTH($A33,0)) + SUMIFS('Vyral'!F:F,'Vyral'!A:A,">="&EOMONTH($A33,-1)+1,'Vyral'!A:A,"<="&EOMONTH($A33,0)) + SUMIFS('Chime'!F:F,'Chime'!A:A,">="&EOMONTH($A33,-1)+1,'Chime'!A:A,"<="&EOMONTH($A33,0)) | E33: =B33-C33-D33 | F33: =SUMIFS('Ghana City'!D:D,'Ghana City'!A:A,">="&EOMONTH($A33,-1)+1,'Ghana City'!A:A,"<="&EOMONTH($A33,0)) | G33: =SUMIFS('Ghana City'!E:E,'Ghana City'!A:A,">="&EOMONTH($A33,-1)+1,'Ghana City'!A:A,"<="&EOMONTH($A33,0)) | H33: =SUMIFS('Ghana City'!F:F,'Ghana City'!A:A,">="&EOMONTH($A33,-1)+1,'Ghana City'!A:A,"<="&EOMONTH($A33,0)) | I33: =F33-G33-H33 | J33: =SUMIFS('Credit Card 1'!D:D,'Credit Card 1'!A:A,">="&EOMONTH($A33,-1)+1,'Credit Card 1'!A:A,"<="&EOMONTH($A33,0)) + SUMIFS('Credit Card 2'!D:D,'Credit Card 2'!A:A,">="&EOMONTH($A33,-1)+1,'Credit Card 2'!A:A,"<="&EOMONTH($A33,0)) | K33: =SUMIFS('Credit Card 1'!E:E,'Credit Card 1'!A:A,">="&EOMONTH($A33,-1)+1,'Credit Card 1'!A:A,"<="&EOMONTH($A33,0)) + SUMIFS('Credit Card 2'!E:E,'Credit Card 2'!A:A,">="&EOMONTH($A33,-1)+1,'Credit Card 2'!A:A,"<="&EOMONTH($A33,0)) | L33: =SUMIFS('Credit Card 1'!F:F,'Credit Card 1'!A:A,">="&EOMONTH($A33,-1)+1,'Credit Card 1'!A:A,"<="&EOMONTH($A33,0)) + SUMIFS('Credit Card 2'!F:F,'Credit Card 2'!A:A,">="&EOMONTH($A33,-1)+1,'Credit Card 2'!A:A,"<="&EOMONTH($A33,0)) | M33: =K33+L33-J33
A34: 46235 | B34: =SUMIFS('Current'!D:D,'Current'!A:A,">="&EOMONTH($A34,-1)+1,'Current'!A:A,"<="&EOMONTH($A34,0)) + SUMIFS('Chase'!D:D,'Chase'!A:A,">="&EOMONTH($A34,-1)+1,'Chase'!A:A,"<="&EOMONTH($A34,0)) + SUMIFS('Wellsfargo'!D:D,'Wellsfargo'!A:A,">="&EOMONTH($A34,-1)+1,'Wellsfargo'!A:A,"<="&EOMONTH($A34,0)) + SUMIFS('Vyral'!D:D,'Vyral'!A:A,">="&EOMONTH($A34,-1)+1,'Vyral'!A:A,"<="&EOMONTH($A34,0)) + SUMIFS('Chime'!D:D,'Chime'!A:A,">="&EOMONTH($A34,-1)+1,'Chime'!A:A,"<="&EOMONTH($A34,0)) | C34: =SUMIFS('Current'!E:E,'Current'!A:A,">="&EOMONTH($A34,-1)+1,'Current'!A:A,"<="&EOMONTH($A34,0)) + SUMIFS('Chase'!E:E,'Chase'!A:A,">="&EOMONTH($A34,-1)+1,'Chase'!A:A,"<="&EOMONTH($A34,0)) + SUMIFS('Wellsfargo'!E:E,'Wellsfargo'!A:A,">="&EOMONTH($A34,-1)+1,'Wellsfargo'!A:A,"<="&EOMONTH($A34,0)) + SUMIFS('Vyral'!E:E,'Vyral'!A:A,">="&EOMONTH($A34,-1)+1,'Vyral'!A:A,"<="&EOMONTH($A34,0)) + SUMIFS('Chime'!E:E,'Chime'!A:A,">="&EOMONTH($A34,-1)+1,'Chime'!A:A,"<="&EOMONTH($A34,0)) | D34: =SUMIFS('Current'!F:F,'Current'!A:A,">="&EOMONTH($A34,-1)+1,'Current'!A:A,"<="&EOMONTH($A34,0)) + SUMIFS('Chase'!F:F,'Chase'!A:A,">="&EOMONTH($A34,-1)+1,'Chase'!A:A,"<="&EOMONTH($A34,0)) + SUMIFS('Wellsfargo'!F:F,'Wellsfargo'!A:A,">="&EOMONTH($A34,-1)+1,'Wellsfargo'!A:A,"<="&EOMONTH($A34,0)) + SUMIFS('Vyral'!F:F,'Vyral'!A:A,">="&EOMONTH($A34,-1)+1,'Vyral'!A:A,"<="&EOMONTH($A34,0)) + SUMIFS('Chime'!F:F,'Chime'!A:A,">="&EOMONTH($A34,-1)+1,'Chime'!A:A,"<="&EOMONTH($A34,0)) | E34: =B34-C34-D34 | F34: =SUMIFS('Ghana City'!D:D,'Ghana City'!A:A,">="&EOMONTH($A34,-1)+1,'Ghana City'!A:A,"<="&EOMONTH($A34,0)) | G34: =SUMIFS('Ghana City'!E:E,'Ghana City'!A:A,">="&EOMONTH($A34,-1)+1,'Ghana City'!A:A,"<="&EOMONTH($A34,0)) | H34: =SUMIFS('Ghana City'!F:F,'Ghana City'!A:A,">="&EOMONTH($A34,-1)+1,'Ghana City'!A:A,"<="&EOMONTH($A34,0)) | I34: =F34-G34-H34 | J34: =SUMIFS('Credit Card 1'!D:D,'Credit Card 1'!A:A,">="&EOMONTH($A34,-1)+1,'Credit Card 1'!A:A,"<="&EOMONTH($A34,0)) + SUMIFS('Credit Card 2'!D:D,'Credit Card 2'!A:A,">="&EOMONTH($A34,-1)+1,'Credit Card 2'!A:A,"<="&EOMONTH($A34,0)) | K34: =SUMIFS('Credit Card 1'!E:E,'Credit Card 1'!A:A,">="&EOMONTH($A34,-1)+1,'Credit Card 1'!A:A,"<="&EOMONTH($A34,0)) + SUMIFS('Credit Card 2'!E:E,'Credit Card 2'!A:A,">="&EOMONTH($A34,-1)+1,'Credit Card 2'!A:A,"<="&EOMONTH($A34,0)) | L34: =SUMIFS('Credit Card 1'!F:F,'Credit Card 1'!A:A,">="&EOMONTH($A34,-1)+1,'Credit Card 1'!A:A,"<="&EOMONTH($A34,0)) + SUMIFS('Credit Card 2'!F:F,'Credit Card 2'!A:A,">="&EOMONTH($A34,-1)+1,'Credit Card 2'!A:A,"<="&EOMONTH($A34,0)) | M34: =K34+L34-J34
A35: 46266 | B35: =SUMIFS('Current'!D:D,'Current'!A:A,">="&EOMONTH($A35,-1)+1,'Current'!A:A,"<="&EOMONTH($A35,0)) + SUMIFS('Chase'!D:D,'Chase'!A:A,">="&EOMONTH($A35,-1)+1,'Chase'!A:A,"<="&EOMONTH($A35,0)) + SUMIFS('Wellsfargo'!D:D,'Wellsfargo'!A:A,">="&EOMONTH($A35,-1)+1,'Wellsfargo'!A:A,"<="&EOMONTH($A35,0)) + SUMIFS('Vyral'!D:D,'Vyral'!A:A,">="&EOMONTH($A35,-1)+1,'Vyral'!A:A,"<="&EOMONTH($A35,0)) + SUMIFS('Chime'!D:D,'Chime'!A:A,">="&EOMONTH($A35,-1)+1,'Chime'!A:A,"<="&EOMONTH($A35,0)) | C35: =SUMIFS('Current'!E:E,'Current'!A:A,">="&EOMONTH($A35,-1)+1,'Current'!A:A,"<="&EOMONTH($A35,0)) + SUMIFS('Chase'!E:E,'Chase'!A:A,">="&EOMONTH($A35,-1)+1,'Chase'!A:A,"<="&EOMONTH($A35,0)) + SUMIFS('Wellsfargo'!E:E,'Wellsfargo'!A:A,">="&EOMONTH($A35,-1)+1,'Wellsfargo'!A:A,"<="&EOMONTH($A35,0)) + SUMIFS('Vyral'!E:E,'Vyral'!A:A,">="&EOMONTH($A35,-1)+1,'Vyral'!A:A,"<="&EOMONTH($A35,0)) + SUMIFS('Chime'!E:E,'Chime'!A:A,">="&EOMONTH($A35,-1)+1,'Chime'!A:A,"<="&EOMONTH($A35,0)) | D35: =SUMIFS('Current'!F:F,'Current'!A:A,">="&EOMONTH($A35,-1)+1,'Current'!A:A,"<="&EOMONTH($A35,0)) + SUMIFS('Chase'!F:F,'Chase'!A:A,">="&EOMONTH($A35,-1)+1,'Chase'!A:A,"<="&EOMONTH($A35,0)) + SUMIFS('Wellsfargo'!F:F,'Wellsfargo'!A:A,">="&EOMONTH($A35,-1)+1,'Wellsfargo'!A:A,"<="&EOMONTH($A35,0)) + SUMIFS('Vyral'!F:F,'Vyral'!A:A,">="&EOMONTH($A35,-1)+1,'Vyral'!A:A,"<="&EOMONTH($A35,0)) + SUMIFS('Chime'!F:F,'Chime'!A:A,">="&EOMONTH($A35,-1)+1,'Chime'!A:A,"<="&EOMONTH($A35,0)) | E35: =B35-C35-D35 | F35: =SUMIFS('Ghana City'!D:D,'Ghana City'!A:A,">="&EOMONTH($A35,-1)+1,'Ghana City'!A:A,"<="&EOMONTH($A35,0)) | G35: =SUMIFS('Ghana City'!E:E,'Ghana City'!A:A,">="&EOMONTH($A35,-1)+1,'Ghana City'!A:A,"<="&EOMONTH($A35,0)) | H35: =SUMIFS('Ghana City'!F:F,'Ghana City'!A:A,">="&EOMONTH($A35,-1)+1,'Ghana City'!A:A,"<="&EOMONTH($A35,0)) | I35: =F35-G35-H35 | J35: =SUMIFS('Credit Card 1'!D:D,'Credit Card 1'!A:A,">="&EOMONTH($A35,-1)+1,'Credit Card 1'!A:A,"<="&EOMONTH($A35,0)) + SUMIFS('Credit Card 2'!D:D,'Credit Card 2'!A:A,">="&EOMONTH($A35,-1)+1,'Credit Card 2'!A:A,"<="&EOMONTH($A35,0)) | K35: =SUMIFS('Credit Card 1'!E:E,'Credit Card 1'!A:A,">="&EOMONTH($A35,-1)+1,'Credit Card 1'!A:A,"<="&EOMONTH($A35,0)) + SUMIFS('Credit Card 2'!E:E,'Credit Card 2'!A:A,">="&EOMONTH($A35,-1)+1,'Credit Card 2'!A:A,"<="&EOMONTH($A35,0)) | L35: =SUMIFS('Credit Card 1'!F:F,'Credit Card 1'!A:A,">="&EOMONTH($A35,-1)+1,'Credit Card 1'!A:A,"<="&EOMONTH($A35,0)) + SUMIFS('Credit Card 2'!F:F,'Credit Card 2'!A:A,">="&EOMONTH($A35,-1)+1,'Credit Card 2'!A:A,"<="&EOMONTH($A35,0)) | M35: =K35+L35-J35
A36: 46296 | B36: =SUMIFS('Current'!D:D,'Current'!A:A,">="&EOMONTH($A36,-1)+1,'Current'!A:A,"<="&EOMONTH($A36,0)) + SUMIFS('Chase'!D:D,'Chase'!A:A,">="&EOMONTH($A36,-1)+1,'Chase'!A:A,"<="&EOMONTH($A36,0)) + SUMIFS('Wellsfargo'!D:D,'Wellsfargo'!A:A,">="&EOMONTH($A36,-1)+1,'Wellsfargo'!A:A,"<="&EOMONTH($A36,0)) + SUMIFS('Vyral'!D:D,'Vyral'!A:A,">="&EOMONTH($A36,-1)+1,'Vyral'!A:A,"<="&EOMONTH($A36,0)) + SUMIFS('Chime'!D:D,'Chime'!A:A,">="&EOMONTH($A36,-1)+1,'Chime'!A:A,"<="&EOMONTH($A36,0)) | C36: =SUMIFS('Current'!E:E,'Current'!A:A,">="&EOMONTH($A36,-1)+1,'Current'!A:A,"<="&EOMONTH($A36,0)) + SUMIFS('Chase'!E:E,'Chase'!A:A,">="&EOMONTH($A36,-1)+1,'Chase'!A:A,"<="&EOMONTH($A36,0)) + SUMIFS('Wellsfargo'!E:E,'Wellsfargo'!A:A,">="&EOMONTH($A36,-1)+1,'Wellsfargo'!A:A,"<="&EOMONTH($A36,0)) + SUMIFS('Vyral'!E:E,'Vyral'!A:A,">="&EOMONTH($A36,-1)+1,'Vyral'!A:A,"<="&EOMONTH($A36,0)) + SUMIFS('Chime'!E:E,'Chime'!A:A,">="&EOMONTH($A36,-1)+1,'Chime'!A:A,"<="&EOMONTH($A36,0)) | D36: =SUMIFS('Current'!F:F,'Current'!A:A,">="&EOMONTH($A36,-1)+1,'Current'!A:A,"<="&EOMONTH($A36,0)) + SUMIFS('Chase'!F:F,'Chase'!A:A,">="&EOMONTH($A36,-1)+1,'Chase'!A:A,"<="&EOMONTH($A36,0)) + SUMIFS('Wellsfargo'!F:F,'Wellsfargo'!A:A,">="&EOMONTH($A36,-1)+1,'Wellsfargo'!A:A,"<="&EOMONTH($A36,0)) + SUMIFS('Vyral'!F:F,'Vyral'!A:A,">="&EOMONTH($A36,-1)+1,'Vyral'!A:A,"<="&EOMONTH($A36,0)) + SUMIFS('Chime'!F:F,'Chime'!A:A,">="&EOMONTH($A36,-1)+1,'Chime'!A:A,"<="&EOMONTH($A36,0)) | E36: =B36-C36-D36 | F36: =SUMIFS('Ghana City'!D:D,'Ghana City'!A:A,">="&EOMONTH($A36,-1)+1,'Ghana City'!A:A,"<="&EOMONTH($A36,0)) | G36: =SUMIFS('Ghana City'!E:E,'Ghana City'!A:A,">="&EOMONTH($A36,-1)+1,'Ghana City'!A:A,"<="&EOMONTH($A36,0)) | H36: =SUMIFS('Ghana City'!F:F,'Ghana City'!A:A,">="&EOMONTH($A36,-1)+1,'Ghana City'!A:A,"<="&EOMONTH($A36,0)) | I36: =F36-G36-H36 | J36: =SUMIFS('Credit Card 1'!D:D,'Credit Card 1'!A:A,">="&EOMONTH($A36,-1)+1,'Credit Card 1'!A:A,"<="&EOMONTH($A36,0)) + SUMIFS('Credit Card 2'!D:D,'Credit Card 2'!A:A,">="&EOMONTH($A36,-1)+1,'Credit Card 2'!A:A,"<="&EOMONTH($A36,0)) | K36: =SUMIFS('Credit Card 1'!E:E,'Credit Card 1'!A:A,">="&EOMONTH($A36,-1)+1,'Credit Card 1'!A:A,"<="&EOMONTH($A36,0)) + SUMIFS('Credit Card 2'!E:E,'Credit Card 2'!A:A,">="&EOMONTH($A36,-1)+1,'Credit Card 2'!A:A,"<="&EOMONTH($A36,0)) | L36: =SUMIFS('Credit Card 1'!F:F,'Credit Card 1'!A:A,">="&EOMONTH($A36,-1)+1,'Credit Card 1'!A:A,"<="&EOMONTH($A36,0)) + SUMIFS('Credit Card 2'!F:F,'Credit Card 2'!A:A,">="&EOMONTH($A36,-1)+1,'Credit Card 2'!A:A,"<="&EOMONTH($A36,0)) | M36: =K36+L36-J36
A37: 46327 | B37: =SUMIFS('Current'!D:D,'Current'!A:A,">="&EOMONTH($A37,-1)+1,'Current'!A:A,"<="&EOMONTH($A37,0)) + SUMIFS('Chase'!D:D,'Chase'!A:A,">="&EOMONTH($A37,-1)+1,'Chase'!A:A,"<="&EOMONTH($A37,0)) + SUMIFS('Wellsfargo'!D:D,'Wellsfargo'!A:A,">="&EOMONTH($A37,-1)+1,'Wellsfargo'!A:A,"<="&EOMONTH($A37,0)) + SUMIFS('Vyral'!D:D,'Vyral'!A:A,">="&EOMONTH($A37,-1)+1,'Vyral'!A:A,"<="&EOMONTH($A37,0)) + SUMIFS('Chime'!D:D,'Chime'!A:A,">="&EOMONTH($A37,-1)+1,'Chime'!A:A,"<="&EOMONTH($A37,0)) | C37: =SUMIFS('Current'!E:E,'Current'!A:A,">="&EOMONTH($A37,-1)+1,'Current'!A:A,"<="&EOMONTH($A37,0)) + SUMIFS('Chase'!E:E,'Chase'!A:A,">="&EOMONTH($A37,-1)+1,'Chase'!A:A,"<="&EOMONTH($A37,0)) + SUMIFS('Wellsfargo'!E:E,'Wellsfargo'!A:A,">="&EOMONTH($A37,-1)+1,'Wellsfargo'!A:A,"<="&EOMONTH($A37,0)) + SUMIFS('Vyral'!E:E,'Vyral'!A:A,">="&EOMONTH($A37,-1)+1,'Vyral'!A:A,"<="&EOMONTH($A37,0)) + SUMIFS('Chime'!E:E,'Chime'!A:A,">="&EOMONTH($A37,-1)+1,'Chime'!A:A,"<="&EOMONTH($A37,0)) | D37: =SUMIFS('Current'!F:F,'Current'!A:A,">="&EOMONTH($A37,-1)+1,'Current'!A:A,"<="&EOMONTH($A37,0)) + SUMIFS('Chase'!F:F,'Chase'!A:A,">="&EOMONTH($A37,-1)+1,'Chase'!A:A,"<="&EOMONTH($A37,0)) + SUMIFS('Wellsfargo'!F:F,'Wellsfargo'!A:A,">="&EOMONTH($A37,-1)+1,'Wellsfargo'!A:A,"<="&EOMONTH($A37,0)) + SUMIFS('Vyral'!F:F,'Vyral'!A:A,">="&EOMONTH($A37,-1)+1,'Vyral'!A:A,"<="&EOMONTH($A37,0)) + SUMIFS('Chime'!F:F,'Chime'!A:A,">="&EOMONTH($A37,-1)+1,'Chime'!A:A,"<="&EOMONTH($A37,0)) | E37: =B37-C37-D37 | F37: =SUMIFS('Ghana City'!D:D,'Ghana City'!A:A,">="&EOMONTH($A37,-1)+1,'Ghana City'!A:A,"<="&EOMONTH($A37,0)) | G37: =SUMIFS('Ghana City'!E:E,'Ghana City'!A:A,">="&EOMONTH($A37,-1)+1,'Ghana City'!A:A,"<="&EOMONTH($A37,0)) | H37: =SUMIFS('Ghana City'!F:F,'Ghana City'!A:A,">="&EOMONTH($A37,-1)+1,'Ghana City'!A:A,"<="&EOMONTH($A37,0)) | I37: =F37-G37-H37 | J37: =SUMIFS('Credit Card 1'!D:D,'Credit Card 1'!A:A,">="&EOMONTH($A37,-1)+1,'Credit Card 1'!A:A,"<="&EOMONTH($A37,0)) + SUMIFS('Credit Card 2'!D:D,'Credit Card 2'!A:A,">="&EOMONTH($A37,-1)+1,'Credit Card 2'!A:A,"<="&EOMONTH($A37,0)) | K37: =SUMIFS('Credit Card 1'!E:E,'Credit Card 1'!A:A,">="&EOMONTH($A37,-1)+1,'Credit Card 1'!A:A,"<="&EOMONTH($A37,0)) + SUMIFS('Credit Card 2'!E:E,'Credit Card 2'!A:A,">="&EOMONTH($A37,-1)+1,'Credit Card 2'!A:A,"<="&EOMONTH($A37,0)) | L37: =SUMIFS('Credit Card 1'!F:F,'Credit Card 1'!A:A,">="&EOMONTH($A37,-1)+1,'Credit Card 1'!A:A,"<="&EOMONTH($A37,0)) + SUMIFS('Credit Card 2'!F:F,'Credit Card 2'!A:A,">="&EOMONTH($A37,-1)+1,'Credit Card 2'!A:A,"<="&EOMONTH($A37,0)) | M37: =K37+L37-J37
A38: 46357 | B38: =SUMIFS('Current'!D:D,'Current'!A:A,">="&EOMONTH($A38,-1)+1,'Current'!A:A,"<="&EOMONTH($A38,0)) + SUMIFS('Chase'!D:D,'Chase'!A:A,">="&EOMONTH($A38,-1)+1,'Chase'!A:A,"<="&EOMONTH($A38,0)) + SUMIFS('Wellsfargo'!D:D,'Wellsfargo'!A:A,">="&EOMONTH($A38,-1)+1,'Wellsfargo'!A:A,"<="&EOMONTH($A38,0)) + SUMIFS('Vyral'!D:D,'Vyral'!A:A,">="&EOMONTH($A38,-1)+1,'Vyral'!A:A,"<="&EOMONTH($A38,0)) + SUMIFS('Chime'!D:D,'Chime'!A:A,">="&EOMONTH($A38,-1)+1,'Chime'!A:A,"<="&EOMONTH($A38,0)) | C38: =SUMIFS('Current'!E:E,'Current'!A:A,">="&EOMONTH($A38,-1)+1,'Current'!A:A,"<="&EOMONTH($A38,0)) + SUMIFS('Chase'!E:E,'Chase'!A:A,">="&EOMONTH($A38,-1)+1,'Chase'!A:A,"<="&EOMONTH($A38,0)) + SUMIFS('Wellsfargo'!E:E,'Wellsfargo'!A:A,">="&EOMONTH($A38,-1)+1,'Wellsfargo'!A:A,"<="&EOMONTH($A38,0)) + SUMIFS('Vyral'!E:E,'Vyral'!A:A,">="&EOMONTH($A38,-1)+1,'Vyral'!A:A,"<="&EOMONTH($A38,0)) + SUMIFS('Chime'!E:E,'Chime'!A:A,">="&EOMONTH($A38,-1)+1,'Chime'!A:A,"<="&EOMONTH($A38,0)) | D38: =SUMIFS('Current'!F:F,'Current'!A:A,">="&EOMONTH($A38,-1)+1,'Current'!A:A,"<="&EOMONTH($A38,0)) + SUMIFS('Chase'!F:F,'Chase'!A:A,">="&EOMONTH($A38,-1)+1,'Chase'!A:A,"<="&EOMONTH($A38,0)) + SUMIFS('Wellsfargo'!F:F,'Wellsfargo'!A:A,">="&EOMONTH($A38,-1)+1,'Wellsfargo'!A:A,"<="&EOMONTH($A38,0)) + SUMIFS('Vyral'!F:F,'Vyral'!A:A,">="&EOMONTH($A38,-1)+1,'Vyral'!A:A,"<="&EOMONTH($A38,0)) + SUMIFS('Chime'!F:F,'Chime'!A:A,">="&EOMONTH($A38,-1)+1,'Chime'!A:A,"<="&EOMONTH($A38,0)) | E38: =B38-C38-D38 | F38: =SUMIFS('Ghana City'!D:D,'Ghana City'!A:A,">="&EOMONTH($A38,-1)+1,'Ghana City'!A:A,"<="&EOMONTH($A38,0)) | G38: =SUMIFS('Ghana City'!E:E,'Ghana City'!A:A,">="&EOMONTH($A38,-1)+1,'Ghana City'!A:A,"<="&EOMONTH($A38,0)) | H38: =SUMIFS('Ghana City'!F:F,'Ghana City'!A:A,">="&EOMONTH($A38,-1)+1,'Ghana City'!A:A,"<="&EOMONTH($A38,0)) | I38: =F38-G38-H38 | J38: =SUMIFS('Credit Card 1'!D:D,'Credit Card 1'!A:A,">="&EOMONTH($A38,-1)+1,'Credit Card 1'!A:A,"<="&EOMONTH($A38,0)) + SUMIFS('Credit Card 2'!D:D,'Credit Card 2'!A:A,">="&EOMONTH($A38,-1)+1,'Credit Card 2'!A:A,"<="&EOMONTH($A38,0)) | K38: =SUMIFS('Credit Card 1'!E:E,'Credit Card 1'!A:A,">="&EOMONTH($A38,-1)+1,'Credit Card 1'!A:A,"<="&EOMONTH($A38,0)) + SUMIFS('Credit Card 2'!E:E,'Credit Card 2'!A:A,">="&EOMONTH($A38,-1)+1,'Credit Card 2'!A:A,"<="&EOMONTH($A38,0)) | L38: =SUMIFS('Credit Card 1'!F:F,'Credit Card 1'!A:A,">="&EOMONTH($A38,-1)+1,'Credit Card 1'!A:A,"<="&EOMONTH($A38,0)) + SUMIFS('Credit Card 2'!F:F,'Credit Card 2'!A:A,">="&EOMONTH($A38,-1)+1,'Credit Card 2'!A:A,"<="&EOMONTH($A38,0)) | M38: =K38+L38-J38
A39: 46388 | B39: =SUMIFS('Current'!D:D,'Current'!A:A,">="&EOMONTH($A39,-1)+1,'Current'!A:A,"<="&EOMONTH($A39,0)) + SUMIFS('Chase'!D:D,'Chase'!A:A,">="&EOMONTH($A39,-1)+1,'Chase'!A:A,"<="&EOMONTH($A39,0)) + SUMIFS('Wellsfargo'!D:D,'Wellsfargo'!A:A,">="&EOMONTH($A39,-1)+1,'Wellsfargo'!A:A,"<="&EOMONTH($A39,0)) + SUMIFS('Vyral'!D:D,'Vyral'!A:A,">="&EOMONTH($A39,-1)+1,'Vyral'!A:A,"<="&EOMONTH($A39,0)) + SUMIFS('Chime'!D:D,'Chime'!A:A,">="&EOMONTH($A39,-1)+1,'Chime'!A:A,"<="&EOMONTH($A39,0)) | C39: =SUMIFS('Current'!E:E,'Current'!A:A,">="&EOMONTH($A39,-1)+1,'Current'!A:A,"<="&EOMONTH($A39,0)) + SUMIFS('Chase'!E:E,'Chase'!A:A,">="&EOMONTH($A39,-1)+1,'Chase'!A:A,"<="&EOMONTH($A39,0)) + SUMIFS('Wellsfargo'!E:E,'Wellsfargo'!A:A,">="&EOMONTH($A39,-1)+1,'Wellsfargo'!A:A,"<="&EOMONTH($A39,0)) + SUMIFS('Vyral'!E:E,'Vyral'!A:A,">="&EOMONTH($A39,-1)+1,'Vyral'!A:A,"<="&EOMONTH($A39,0)) + SUMIFS('Chime'!E:E,'Chime'!A:A,">="&EOMONTH($A39,-1)+1,'Chime'!A:A,"<="&EOMONTH($A39,0)) | D39: =SUMIFS('Current'!F:F,'Current'!A:A,">="&EOMONTH($A39,-1)+1,'Current'!A:A,"<="&EOMONTH($A39,0)) + SUMIFS('Chase'!F:F,'Chase'!A:A,">="&EOMONTH($A39,-1)+1,'Chase'!A:A,"<="&EOMONTH($A39,0)) + SUMIFS('Wellsfargo'!F:F,'Wellsfargo'!A:A,">="&EOMONTH($A39,-1)+1,'Wellsfargo'!A:A,"<="&EOMONTH($A39,0)) + SUMIFS('Vyral'!F:F,'Vyral'!A:A,">="&EOMONTH($A39,-1)+1,'Vyral'!A:A,"<="&EOMONTH($A39,0)) + SUMIFS('Chime'!F:F,'Chime'!A:A,">="&EOMONTH($A39,-1)+1,'Chime'!A:A,"<="&EOMONTH($A39,0)) | E39: =B39-C39-D39 | F39: =SUMIFS('Ghana City'!D:D,'Ghana City'!A:A,">="&EOMONTH($A39,-1)+1,'Ghana City'!A:A,"<="&EOMONTH($A39,0)) | G39: =SUMIFS('Ghana City'!E:E,'Ghana City'!A:A,">="&EOMONTH($A39,-1)+1,'Ghana City'!A:A,"<="&EOMONTH($A39,0)) | H39: =SUMIFS('Ghana City'!F:F,'Ghana City'!A:A,">="&EOMONTH($A39,-1)+1,'Ghana City'!A:A,"<="&EOMONTH($A39,0)) | I39: =F39-G39-H39 | J39: =SUMIFS('Credit Card 1'!D:D,'Credit Card 1'!A:A,">="&EOMONTH($A39,-1)+1,'Credit Card 1'!A:A,"<="&EOMONTH($A39,0)) + SUMIFS('Credit Card 2'!D:D,'Credit Card 2'!A:A,">="&EOMONTH($A39,-1)+1,'Credit Card 2'!A:A,"<="&EOMONTH($A39,0)) | K39: =SUMIFS('Credit Card 1'!E:E,'Credit Card 1'!A:A,">="&EOMONTH($A39,-1)+1,'Credit Card 1'!A:A,"<="&EOMONTH($A39,0)) + SUMIFS('Credit Card 2'!E:E,'Credit Card 2'!A:A,">="&EOMONTH($A39,-1)+1,'Credit Card 2'!A:A,"<="&EOMONTH($A39,0)) | L39: =SUMIFS('Credit Card 1'!F:F,'Credit Card 1'!A:A,">="&EOMONTH($A39,-1)+1,'Credit Card 1'!A:A,"<="&EOMONTH($A39,0)) + SUMIFS('Credit Card 2'!F:F,'Credit Card 2'!A:A,">="&EOMONTH($A39,-1)+1,'Credit Card 2'!A:A,"<="&EOMONTH($A39,0)) | M39: =K39+L39-J39
A40: 46419 | B40: =SUMIFS('Current'!D:D,'Current'!A:A,">="&EOMONTH($A40,-1)+1,'Current'!A:A,"<="&EOMONTH($A40,0)) + SUMIFS('Chase'!D:D,'Chase'!A:A,">="&EOMONTH($A40,-1)+1,'Chase'!A:A,"<="&EOMONTH($A40,0)) + SUMIFS('Wellsfargo'!D:D,'Wellsfargo'!A:A,">="&EOMONTH($A40,-1)+1,'Wellsfargo'!A:A,"<="&EOMONTH($A40,0)) + SUMIFS('Vyral'!D:D,'Vyral'!A:A,">="&EOMONTH($A40,-1)+1,'Vyral'!A:A,"<="&EOMONTH($A40,0)) + SUMIFS('Chime'!D:D,'Chime'!A:A,">="&EOMONTH($A40,-1)+1,'Chime'!A:A,"<="&EOMONTH($A40,0)) | C40: =SUMIFS('Current'!E:E,'Current'!A:A,">="&EOMONTH($A40,-1)+1,'Current'!A:A,"<="&EOMONTH($A40,0)) + SUMIFS('Chase'!E:E,'Chase'!A:A,">="&EOMONTH($A40,-1)+1,'Chase'!A:A,"<="&EOMONTH($A40,0)) + SUMIFS('Wellsfargo'!E:E,'Wellsfargo'!A:A,">="&EOMONTH($A40,-1)+1,'Wellsfargo'!A:A,"<="&EOMONTH($A40,0)) + SUMIFS('Vyral'!E:E,'Vyral'!A:A,">="&EOMONTH($A40,-1)+1,'Vyral'!A:A,"<="&EOMONTH($A40,0)) + SUMIFS('Chime'!E:E,'Chime'!A:A,">="&EOMONTH($A40,-1)+1,'Chime'!A:A,"<="&EOMONTH($A40,0)) | D40: =SUMIFS('Current'!F:F,'Current'!A:A,">="&EOMONTH($A40,-1)+1,'Current'!A:A,"<="&EOMONTH($A40,0)) + SUMIFS('Chase'!F:F,'Chase'!A:A,">="&EOMONTH($A40,-1)+1,'Chase'!A:A,"<="&EOMONTH($A40,0)) + SUMIFS('Wellsfargo'!F:F,'Wellsfargo'!A:A,">="&EOMONTH($A40,-1)+1,'Wellsfargo'!A:A,"<="&EOMONTH($A40,0)) + SUMIFS('Vyral'!F:F,'Vyral'!A:A,">="&EOMONTH($A40,-1)+1,'Vyral'!A:A,"<="&EOMONTH($A40,0)) + SUMIFS('Chime'!F:F,'Chime'!A:A,">="&EOMONTH($A40,-1)+1,'Chime'!A:A,"<="&EOMONTH($A40,0)) | E40: =B40-C40-D40 | F40: =SUMIFS('Ghana City'!D:D,'Ghana City'!A:A,">="&EOMONTH($A40,-1)+1,'Ghana City'!A:A,"<="&EOMONTH($A40,0)) | G40: =SUMIFS('Ghana City'!E:E,'Ghana City'!A:A,">="&EOMONTH($A40,-1)+1,'Ghana City'!A:A,"<="&EOMONTH($A40,0)) | H40: =SUMIFS('Ghana City'!F:F,'Ghana City'!A:A,">="&EOMONTH($A40,-1)+1,'Ghana City'!A:A,"<="&EOMONTH($A40,0)) | I40: =F40-G40-H40 | J40: =SUMIFS('Credit Card 1'!D:D,'Credit Card 1'!A:A,">="&EOMONTH($A40,-1)+1,'Credit Card 1'!A:A,"<="&EOMONTH($A40,0)) + SUMIFS('Credit Card 2'!D:D,'Credit Card 2'!A:A,">="&EOMONTH($A40,-1)+1,'Credit Card 2'!A:A,"<="&EOMONTH($A40,0)) | K40: =SUMIFS('Credit Card 1'!E:E,'Credit Card 1'!A:A,">="&EOMONTH($A40,-1)+1,'Credit Card 1'!A:A,"<="&EOMONTH($A40,0)) + SUMIFS('Credit Card 2'!E:E,'Credit Card 2'!A:A,">="&EOMONTH($A40,-1)+1,'Credit Card 2'!A:A,"<="&EOMONTH($A40,0)) | L40: =SUMIFS('Credit Card 1'!F:F,'Credit Card 1'!A:A,">="&EOMONTH($A40,-1)+1,'Credit Card 1'!A:A,"<="&EOMONTH($A40,0)) + SUMIFS('Credit Card 2'!F:F,'Credit Card 2'!A:A,">="&EOMONTH($A40,-1)+1,'Credit Card 2'!A:A,"<="&EOMONTH($A40,0)) | M40: =K40+L40-J40
A41: 46447 | B41: =SUMIFS('Current'!D:D,'Current'!A:A,">="&EOMONTH($A41,-1)+1,'Current'!A:A,"<="&EOMONTH($A41,0)) + SUMIFS('Chase'!D:D,'Chase'!A:A,">="&EOMONTH($A41,-1)+1,'Chase'!A:A,"<="&EOMONTH($A41,0)) + SUMIFS('Wellsfargo'!D:D,'Wellsfargo'!A:A,">="&EOMONTH($A41,-1)+1,'Wellsfargo'!A:A,"<="&EOMONTH($A41,0)) + SUMIFS('Vyral'!D:D,'Vyral'!A:A,">="&EOMONTH($A41,-1)+1,'Vyral'!A:A,"<="&EOMONTH($A41,0)) + SUMIFS('Chime'!D:D,'Chime'!A:A,">="&EOMONTH($A41,-1)+1,'Chime'!A:A,"<="&EOMONTH($A41,0)) | C41: =SUMIFS('Current'!E:E,'Current'!A:A,">="&EOMONTH($A41,-1)+1,'Current'!A:A,"<="&EOMONTH($A41,0)) + SUMIFS('Chase'!E:E,'Chase'!A:A,">="&EOMONTH($A41,-1)+1,'Chase'!A:A,"<="&EOMONTH($A41,0)) + SUMIFS('Wellsfargo'!E:E,'Wellsfargo'!A:A,">="&EOMONTH($A41,-1)+1,'Wellsfargo'!A:A,"<="&EOMONTH($A41,0)) + SUMIFS('Vyral'!E:E,'Vyral'!A:A,">="&EOMONTH($A41,-1)+1,'Vyral'!A:A,"<="&EOMONTH($A41,0)) + SUMIFS('Chime'!E:E,'Chime'!A:A,">="&EOMONTH($A41,-1)+1,'Chime'!A:A,"<="&EOMONTH($A41,0)) | D41: =SUMIFS('Current'!F:F,'Current'!A:A,">="&EOMONTH($A41,-1)+1,'Current'!A:A,"<="&EOMONTH($A41,0)) + SUMIFS('Chase'!F:F,'Chase'!A:A,">="&EOMONTH($A41,-1)+1,'Chase'!A:A,"<="&EOMONTH($A41,0)) + SUMIFS('Wellsfargo'!F:F,'Wellsfargo'!A:A,">="&EOMONTH($A41,-1)+1,'Wellsfargo'!A:A,"<="&EOMONTH($A41,0)) + SUMIFS('Vyral'!F:F,'Vyral'!A:A,">="&EOMONTH($A41,-1)+1,'Vyral'!A:A,"<="&EOMONTH($A41,0)) + SUMIFS('Chime'!F:F,'Chime'!A:A,">="&EOMONTH($A41,-1)+1,'Chime'!A:A,"<="&EOMONTH($A41,0)) | E41: =B41-C41-D41 | F41: =SUMIFS('Ghana City'!D:D,'Ghana City'!A:A,">="&EOMONTH($A41,-1)+1,'Ghana City'!A:A,"<="&EOMONTH($A41,0)) | G41: =SUMIFS('Ghana City'!E:E,'Ghana City'!A:A,">="&EOMONTH($A41,-1)+1,'Ghana City'!A:A,"<="&EOMONTH($A41,0)) | H41: =SUMIFS('Ghana City'!F:F,'Ghana City'!A:A,">="&EOMONTH($A41,-1)+1,'Ghana City'!A:A,"<="&EOMONTH($A41,0)) | I41: =F41-G41-H41 | J41: =SUMIFS('Credit Card 1'!D:D,'Credit Card 1'!A:A,">="&EOMONTH($A41,-1)+1,'Credit Card 1'!A:A,"<="&EOMONTH($A41,0)) + SUMIFS('Credit Card 2'!D:D,'Credit Card 2'!A:A,">="&EOMONTH($A41,-1)+1,'Credit Card 2'!A:A,"<="&EOMONTH($A41,0)) | K41: =SUMIFS('Credit Card 1'!E:E,'Credit Card 1'!A:A,">="&EOMONTH($A41,-1)+1,'Credit Card 1'!A:A,"<="&EOMONTH($A41,0)) + SUMIFS('Credit Card 2'!E:E,'Credit Card 2'!A:A,">="&EOMONTH($A41,-1)+1,'Credit Card 2'!A:A,"<="&EOMONTH($A41,0)) | L41: =SUMIFS('Credit Card 1'!F:F,'Credit Card 1'!A:A,">="&EOMONTH($A41,-1)+1,'Credit Card 1'!A:A,"<="&EOMONTH($A41,0)) + SUMIFS('Credit Card 2'!F:F,'Credit Card 2'!A:A,">="&EOMONTH($A41,-1)+1,'Credit Card 2'!A:A,"<="&EOMONTH($A41,0)) | M41: =K41+L41-J41
... A66: 47209 | B66: =SUMIFS('Current'!D:D,'Current'!A:A,">="&EOMONTH($A66,-1)+1,'Current'!A:A,"<="&EOMONTH($A66,0)) + SUMIFS('Chase'!D:D,'Chase'!A:A,">="&EOMONTH($A66,-1)+1,'Chase'!A:A,"<="&EOMONTH($A66,0)) + SUMIFS('Wellsfargo'!D:D,'Wellsfargo'!A:A,">="&EOMONTH($A66,-1)+1,'Wellsfargo'!A:A,"<="&EOMONTH($A66,0)) + SUMIFS('Vyral'!D:D,'Vyral'!A:A,">="&EOMONTH($A66,-1)+1,'Vyral'!A:A,"<="&EOMONTH($A66,0)) + SUMIFS('Chime'!D:D,'Chime'!A:A,">="&EOMONTH($A66,-1)+1,'Chime'!A:A,"<="&EOMONTH($A66,0)) | C66: =SUMIFS('Current'!E:E,'Current'!A:A,">="&EOMONTH($A66,-1)+1,'Current'!A:A,"<="&EOMONTH($A66,0)) + SUMIFS('Chase'!E:E,'Chase'!A:A,">="&EOMONTH($A66,-1)+1,'Chase'!A:A,"<="&EOMONTH($A66,0)) + SUMIFS('Wellsfargo'!E:E,'Wellsfargo'!A:A,">="&EOMONTH($A66,-1)+1,'Wellsfargo'!A:A,"<="&EOMONTH($A66,0)) + SUMIFS('Vyral'!E:E,'Vyral'!A:A,">="&EOMONTH($A66,-1)+1,'Vyral'!A:A,"<="&EOMONTH($A66,0)) + SUMIFS('Chime'!E:E,'Chime'!A:A,">="&EOMONTH($A66,-1)+1,'Chime'!A:A,"<="&EOMONTH($A66,0)) | D66: =SUMIFS('Current'!F:F,'Current'!A:A,">="&EOMONTH($A66,-1)+1,'Current'!A:A,"<="&EOMONTH($A66,0)) + SUMIFS('Chase'!F:F,'Chase'!A:A,">="&EOMONTH($A66,-1)+1,'Chase'!A:A,"<="&EOMONTH($A66,0)) + SUMIFS('Wellsfargo'!F:F,'Wellsfargo'!A:A,">="&EOMONTH($A66,-1)+1,'Wellsfargo'!A:A,"<="&EOMONTH($A66,0)) + SUMIFS('Vyral'!F:F,'Vyral'!A:A,">="&EOMONTH($A66,-1)+1,'Vyral'!A:A,"<="&EOMONTH($A66,0)) + SUMIFS('Chime'!F:F,'Chime'!A:A,">="&EOMONTH($A66,-1)+1,'Chime'!A:A,"<="&EOMONTH($A66,0)) | E66: =B66-C66-D66 | F66: =SUMIFS('Ghana City'!D:D,'Ghana City'!A:A,">="&EOMONTH($A66,-1)+1,'Ghana City'!A:A,"<="&EOMONTH($A66,0)) | G66: =SUMIFS('Ghana City'!E:E,'Ghana City'!A:A,">="&EOMONTH($A66,-1)+1,'Ghana City'!A:A,"<="&EOMONTH($A66,0)) | H66: =SUMIFS('Ghana City'!F:F,'Ghana City'!A:A,">="&EOMONTH($A66,-1)+1,'Ghana City'!A:A,"<="&EOMONTH($A66,0)) | I66: =F66-G66-H66 | J66: =SUMIFS('Credit Card 1'!D:D,'Credit Card 1'!A:A,">="&EOMONTH($A66,-1)+1,'Credit Card 1'!A:A,"<="&EOMONTH($A66,0)) + SUMIFS('Credit Card 2'!D:D,'Credit Card 2'!A:A,">="&EOMONTH($A66,-1)+1,'Credit Card 2'!A:A,"<="&EOMONTH($A66,0)) | K66: =SUMIFS('Credit Card 1'!E:E,'Credit Card 1'!A:A,">="&EOMONTH($A66,-1)+1,'Credit Card 1'!A:A,"<="&EOMONTH($A66,0)) + SUMIFS('Credit Card 2'!E:E,'Credit Card 2'!A:A,">="&EOMONTH($A66,-1)+1,'Credit Card 2'!A:A,"<="&EOMONTH($A66,0)) | L66: =SUMIFS('Credit Card 1'!F:F,'Credit Card 1'!A:A,">="&EOMONTH($A66,-1)+1,'Credit Card 1'!A:A,"<="&EOMONTH($A66,0)) + SUMIFS('Credit Card 2'!F:F,'Credit Card 2'!A:A,">="&EOMONTH($A66,-1)+1,'Credit Card 2'!A:A,"<="&EOMONTH($A66,0)) | M66: =K66+L66-J66

Sheet Current
A1: Current Account Tracker (USD)
A2: Currency | B2: USD
A3: Starting Balance | B3: 0 | D3: Total Tax Paid | E3: =SUM(F7:F406)
A4: Current Balance | B4: =IFERROR(LOOKUP(2,1/(G7:G406<>""),G7:G406),B3)
A6: Date | B6: Description | C6: Category | D6: Money In | E6: Money Out | F6: Tax | G6: Running Balance | H6: Notes
G7: =IF(COUNTA(A7:F7)=0,"",$B$3+D7-E7-F7)
G8: =IF(COUNTA(A8:F8)=0,"",G7+D8-E8-F8)
G9: =IF(COUNTA(A9:F9)=0,"",G8+D9-E9-F9)
G10: =IF(COUNTA(A10:F10)=0,"",G9+D10-E10-F10)
G11: =IF(COUNTA(A11:F11)=0,"",G10+D11-E11-F11)
G12: =IF(COUNTA(A12:F12)=0,"",G11+D12-E12-F12)
G13: =IF(COUNTA(A13:F13)=0,"",G12+D13-E13-F13)
G14: =IF(COUNTA(A14:F14)=0,"",G13+D14-E14-F14)
G15: =IF(COUNTA(A15:F15)=0,"",G14+D15-E15-F15)
G16: =IF(COUNTA(A16:F16)=0,"",G15+D16-E16-F16)
G17: =IF(COUNTA(A17:F17)=0,"",G16+D17-E17-F17)
G18: =IF(COUNTA(A18:F18)=0,"",G17+D18-E18-F18)
G19: =IF(COUNTA(A19:F19)=0,"",G18+D19-E19-F19)
... G406: =IF(COUNTA(A406:F406)=0,"",G405+D406-E406-F406)

Sheet Chase
A1: Chase Account Tracker (USD)
A2: Currency | B2: USD
A3: Starting Balance | B3: 0 | D3: Total Tax Paid | E3: =SUM(F7:F406)
A4: Current Balance | B4: =IFERROR(LOOKUP(2,1/(G7:G406<>""),G7:G406),B3)
A6: Date | B6: Description | C6: Category | D6: Money In | E6: Money Out | F6: Tax | G6: Running Balance | H6: Notes
G7: =IF(COUNTA(A7:F7)=0,"",$B$3+D7-E7-F7)
G8: =IF(COUNTA(A8:F8)=0,"",G7+D8-E8-F8)
G9: =IF(COUNTA(A9:F9)=0,"",G8+D9-E9-F9)
G10: =IF(COUNTA(A10:F10)=0,"",G9+D10-E10-F10)
G11: =IF(COUNTA(A11:F11)=0,"",G10+D11-E11-F11)
G12: =IF(COUNTA(A12:F12)=0,"",G11+D12-E12-F12)
G13: =IF(COUNTA(A13:F13)=0,"",G12+D13-E13-F13)
G14: =IF(COUNTA(A14:F14)=0,"",G13+D14-E14-F14)
G15: =IF(COUNTA(A15:F15)=0,"",G14+D15-E15-F15)
G16: =IF(COUNTA(A16:F16)=0,"",G15+D16-E16-F16)
G17: =IF(COUNTA(A17:F17)=0,"",G16+D17-E17-F17)
G18: =IF(COUNTA(A18:F18)=0,"",G17+D18-E18-F18)
G19: =IF(COUNTA(A19:F19)=0,"",G18+D19-E19-F19)
... G406: =IF(COUNTA(A406:F406)=0,"",G405+D406-E406-F406)

Sheet Wellsfargo
A1: Wellsfargo Account Tracker (USD)
A2: Currency | B2: USD
A3: Starting Balance | B3: 0 | D3: Total Tax Paid | E3: =SUM(F7:F406)
A4: Current Balance | B4: =IFERROR(LOOKUP(2,1/(G7:G406<>""),G7:G406),B3)
A6: Date | B6: Description | C6: Category | D6: Money In | E6: Money Out | F6: Tax | G6: Running Balance | H6: Notes
G7: =IF(COUNTA(A7:F7)=0,"",$B$3+D7-E7-F7)
G8: =IF(COUNTA(A8:F8)=0,"",G7+D8-E8-F8)
G9: =IF(COUNTA(A9:F9)=0,"",G8+D9-E9-F9)
G10: =IF(COUNTA(A10:F10)=0,"",G9+D10-E10-F10)
G11: =IF(COUNTA(A11:F11)=0,"",G10+D11-E11-F11)
G12: =IF(COUNTA(A12:F12)=0,"",G11+D12-E12-F12)
G13: =IF(COUNTA(A13:F13)=0,"",G12+D13-E13-F13)
G14: =IF(COUNTA(A14:F14)=0,"",G13+D14-E14-F14)
G15: =IF(COUNTA(A15:F15)=0,"",G14+D15-E15-F15)
G16: =IF(COUNTA(A16:F16)=0,"",G15+D16-E16-F16)
G17: =IF(COUNTA(A17:F17)=0,"",G16+D17-E17-F17)
G18: =IF(COUNTA(A18:F18)=0,"",G17+D18-E18-F18)
G19: =IF(COUNTA(A19:F19)=0,"",G18+D19-E19-F19)
... G406: =IF(COUNTA(A406:F406)=0,"",G405+D406-E406-F406)

Sheet Vyral
A1: Vyral Account Tracker (USD)
A2: Currency | B2: USD
A3: Starting Balance | B3: 0 | D3: Total Tax Paid | E3: =SUM(F7:F406)
A4: Current Balance | B4: =IFERROR(LOOKUP(2,1/(G7:G406<>""),G7:G406),B3)
A6: Date | B6: Description | C6: Category | D6: Money In | E6: Money Out | F6: Tax | G6: Running Balance | H6: Notes
G7: =IF(COUNTA(A7:F7)=0,"",$B$3+D7-E7-F7)
G8: =IF(COUNTA(A8:F8)=0,"",G7+D8-E8-F8)
G9: =IF(COUNTA(A9:F9)=0,"",G8+D9-E9-F9)
G10: =IF(COUNTA(A10:F10)=0,"",G9+D10-E10-F10)
G11: =IF(COUNTA(A11:F11)=0,"",G10+D11-E11-F11)
G12: =IF(COUNTA(A12:F12)=0,"",G11+D12-E12-F12)
G13: =IF(COUNTA(A13:F13)=0,"",G12+D13-E13-F13)
G14: =IF(COUNTA(A14:F14)=0,"",G13+D14-E14-F14)
G15: =IF(COUNTA(A15:F15)=0,"",G14+D15-E15-F15)
G16: =IF(COUNTA(A16:F16)=0,"",G15+D16-E16-F16)
G17: =IF(COUNTA(A17:F17)=0,"",G16+D17-E17-F17)
G18: =IF(COUNTA(A18:F18)=0,"",G17+D18-E18-F18)
G19: =IF(COUNTA(A19:F19)=0,"",G18+D19-E19-F19)
... G406: =IF(COUNTA(A406:F406)=0,"",G405+D406-E406-F406)

Sheet Ghana City
A1: Ghana City Account Tracker (GHS)
A2: Currency | B2: GHS
A3: Starting Balance | B3: 0 | D3: Total Tax Paid | E3: =SUM(F7:F406)
A4: Current Balance | B4: =IFERROR(LOOKUP(2,1/(G7:G406<>""),G7:G406),B3)
A6: Date | B6: Description | C6: Category | D6: Money In | E6: Money Out | F6: Tax | G6: Running Balance | H6: Notes
G7: =IF(COUNTA(A7:F7)=0,"",$B$3+D7-E7-F7)
G8: =IF(COUNTA(A8:F8)=0,"",G7+D8-E8-F8)
G9: =IF(COUNTA(A9:F9)=0,"",G8+D9-E9-F9)
G10: =IF(COUNTA(A10:F10)=0,"",G9+D10-E10-F10)
G11: =IF(COUNTA(A11:F11)=0,"",G10+D11-E11-F11)
G12: =IF(COUNTA(A12:F12)=0,"",G11+D12-E12-F12)
G13: =IF(COUNTA(A13:F13)=0,"",G12+D13-E13-F13)
G14: =IF(COUNTA(A14:F14)=0,"",G13+D14-E14-F14)
G15: =IF(COUNTA(A15:F15)=0,"",G14+D15-E15-F15)
G16: =IF(COUNTA(A16:F16)=0,"",G15+D16-E16-F16)
G17: =IF(COUNTA(A17:F17)=0,"",G16+D17-E17-F17)
G18: =IF(COUNTA(A18:F18)=0,"",G17+D18-E18-F18)
G19: =IF(COUNTA(A19:F19)=0,"",G18+D19-E19-F19)
... G406: =IF(COUNTA(A406:F406)=0,"",G405+D406-E406-F406)

Sheet Credit Card 1
A1: Credit Card 1 Tracker (USD)
A2: Currency | B2: USD
A3: Starting Balance Owed | B3: 0 | D3: Total Tax Paid | E3: =SUM(F7:F406)
A4: Current Balance Owed | B4: =IFERROR(LOOKUP(2,1/(G7:G406<>""),G7:G406),B3)
A6: Date | B6: Description | C6: Category | D6: Payment (Money In) | E6: Spend (Money Out) | F6: Tax | G6: Running Balance Owed | H6: Notes
G7: =IF(COUNTA(A7:F7)=0,"",$B$3+E7+F7-D7)
G8: =IF(COUNTA(A8:F8)=0,"",G7+E8+F8-D8)
G9: =IF(COUNTA(A9:F9)=0,"",G8+E9+F9-D9)
G10: =IF(COUNTA(A10:F10)=0,"",G9+E10+F10-D10)
G11: =IF(COUNTA(A11:F11)=0,"",G10+E11+F11-D11)
G12: =IF(COUNTA(A12:F12)=0,"",G11+E12+F12-D12)
G13: =IF(COUNTA(A13:F13)=0,"",G12+E13+F13-D13)
G14: =IF(COUNTA(A14:F14)=0,"",G13+E14+F14-D14)
G15: =IF(COUNTA(A15:F15)=0,"",G14+E15+F15-D15)
G16: =IF(COUNTA(A16:F16)=0,"",G15+E16+F16-D16)
G17: =IF(COUNTA(A17:F17)=0,"",G16+E17+F17-D17)
G18: =IF(COUNTA(A18:F18)=0,"",G17+E18+F18-D18)
G19: =IF(COUNTA(A19:F19)=0,"",G18+E19+F19-D19)
... G406: =IF(COUNTA(A406:F406)=0,"",G405+E406+F406-D406)

Sheet Credit Card 2
A1: Credit Card 2 Tracker (USD)
A2: Currency | B2: USD
A3: Starting Balance Owed | B3: 0 | D3: Total Tax Paid | E3: =SUM(F7:F406)
A4: Current Balance Owed | B4: =IFERROR(LOOKUP(2,1/(G7:G406<>""),G7:G406),B3)
A6: Date | B6: Description | C6: Category | D6: Payment (Money In) | E6: Spend (Money Out) | F6: Tax | G6: Running Balance Owed | H6: Notes
G7: =IF(COUNTA(A7:F7)=0,"",$B$3+E7+F7-D7)
G8: =IF(COUNTA(A8:F8)=0,"",G7+E8+F8-D8)
G9: =IF(COUNTA(A9:F9)=0,"",G8+E9+F9-D9)
G10: =IF(COUNTA(A10:F10)=0,"",G9+E10+F10-D10)
G11: =IF(COUNTA(A11:F11)=0,"",G10+E11+F11-D11)
G12: =IF(COUNTA(A12:F12)=0,"",G11+E12+F12-D12)
G13: =IF(COUNTA(A13:F13)=0,"",G12+E13+F13-D13)
G14: =IF(COUNTA(A14:F14)=0,"",G13+E14+F14-D14)
G15: =IF(COUNTA(A15:F15)=0,"",G14+E15+F15-D15)
G16: =IF(COUNTA(A16:F16)=0,"",G15+E16+F16-D16)
G17: =IF(COUNTA(A17:F17)=0,"",G16+E17+F17-D17)
G18: =IF(COUNTA(A18:F18)=0,"",G17+E18+F18-D18)
G19: =IF(COUNTA(A19:F19)=0,"",G18+E19+F19-D19)
... G406: =IF(COUNTA(A406:F406)=0,"",G405+E406+F406-D406)

Sheet Chime
A1: Chime Account Tracker (USD)
A2: Currency | B2: USD
A3: Starting Balance | B3: 0 | D3: Total Tax Paid | E3: =SUM(F7:F406)
A4: Current Balance | B4: =IFERROR(LOOKUP(2,1/(G7:G406<>""),G7:G406),B3)
A6: Date | B6: Description | C6: Category | D6: Money In | E6: Money Out | F6: Tax | G6: Running Balance | H6: Notes
G7: =IF(COUNTA(A7:F7)=0,"",$B$3+D7-E7-F7)
G8: =IF(COUNTA(A8:F8)=0,"",G7+D8-E8-F8)
G9: =IF(COUNTA(A9:F9)=0,"",G8+D9-E9-F9)
G10: =IF(COUNTA(A10:F10)=0,"",G9+D10-E10-F10)
G11: =IF(COUNTA(A11:F11)=0,"",G10+D11-E11-F11)
G12: =IF(COUNTA(A12:F12)=0,"",G11+D12-E12-F12)
G13: =IF(COUNTA(A13:F13)=0,"",G12+D13-E13-F13)
G14: =IF(COUNTA(A14:F14)=0,"",G13+D14-E14-F14)
G15: =IF(COUNTA(A15:F15)=0,"",G14+D15-E15-F15)
G16: =IF(COUNTA(A16:F16)=0,"",G15+D16-E16-F16)
G17: =IF(COUNTA(A17:F17)=0,"",G16+D17-E17-F17)
G18: =IF(COUNTA(A18:F18)=0,"",G17+D18-E18-F18)
G19: =IF(COUNTA(A19:F19)=0,"",G18+D19-E19-F19)
... G406: =IF(COUNTA(A406:F406)=0,"",G405+D406-E406-F406)
